{"id":43,"name":"resultSchema","kind":32,"kindString":"Variable","flags":{"isConst":true},"comment":{"summary":[{"kind":"inline-tag","tag":"@link","text":"Zod schema","target":"https://zod.dev"},{"kind":"text","text":" for the output of npc callbacks."}],"blockTags":[{"tag":"@see","content":[{"kind":"inline-tag","tag":"@link","text":"Zod","target":"https://zod.dev"}]}]},"children":[],"sources":[{"fileName":"src/index.ts","fullFileName":"/home/runner/work/npc/npc/src/index.ts","line":37,"character":13,"url":"https://github.com/toebeann/npc/blob/06eb126/src/index.ts#L37"}],"type":{"type":"reference","name":"ZodUnknown","qualifiedName":"ZodUnknown","package":"zod"},"defaultValue":"...","is":{"declaration":true},"location":{"query":"Variable.resultSchema","hash":""},"text":{"comment":"<p><a href=\"https://zod.dev\">Zod schema</a> for the output of npc callbacks.</p>\n<h5>See:</h5><p><a href=\"https://zod.dev\">Zod</a></p>\n"}}
